drf_chart_of_account/__init__.py
drf_chart_of_account/admin.py
drf_chart_of_account/apps.py
drf_chart_of_account/models.py
drf_chart_of_account/serializers.py
drf_chart_of_account/urls.py
drf_chart_of_account/views.py
drf_chart_of_account/__pycache__/__init__.cpython-36.pyc
drf_chart_of_account/__pycache__/__init__.cpython-37.pyc
drf_chart_of_account/__pycache__/__init__.cpython-38.pyc
drf_chart_of_account/__pycache__/admin.cpython-36.pyc
drf_chart_of_account/__pycache__/admin.cpython-37.pyc
drf_chart_of_account/__pycache__/admin.cpython-38.pyc
drf_chart_of_account/__pycache__/apps.cpython-36.pyc
drf_chart_of_account/__pycache__/apps.cpython-37.pyc
drf_chart_of_account/__pycache__/apps.cpython-38.pyc
drf_chart_of_account/__pycache__/models.cpython-36.pyc
drf_chart_of_account/__pycache__/models.cpython-37.pyc
drf_chart_of_account/__pycache__/models.cpython-38.pyc
drf_chart_of_account/__pycache__/serializers.cpython-36.pyc
drf_chart_of_account/__pycache__/serializers.cpython-37.pyc
drf_chart_of_account/__pycache__/serializers.cpython-38.pyc
drf_chart_of_account/__pycache__/urls.cpython-36.pyc
drf_chart_of_account/__pycache__/urls.cpython-37.pyc
drf_chart_of_account/__pycache__/urls.cpython-38.pyc
drf_chart_of_account/__pycache__/views.cpython-36.pyc
drf_chart_of_account/__pycache__/views.cpython-37.pyc
drf_chart_of_account/__pycache__/views.cpython-38.pyc
drf_chart_of_account/fixtures/__init__.py
drf_chart_of_account/fixtures/fixture_layer_five_model.json
drf_chart_of_account/fixtures/fixture_layer_four_model.json
drf_chart_of_account/fixtures/fixture_layer_one_model.json
drf_chart_of_account/fixtures/fixture_layer_three_model.json
drf_chart_of_account/fixtures/fixture_layer_two_model.json
drf_chart_of_account/fixtures/__pycache__/__init__.cpython-38.pyc
drf_chart_of_account/migrations/0001_initial.py
drf_chart_of_account/migrations/0002_auto_20201015_1803.py
drf_chart_of_account/migrations/0003_auto_20201015_1921.py
skooby_drf_chart_of_account-1.0.0.dist-info/LICENSE
skooby_drf_chart_of_account-1.0.0.dist-info/METADATA
skooby_drf_chart_of_account-1.0.0.dist-info/WHEEL
skooby_drf_chart_of_account-1.0.0.dist-info/top_level.txt
skooby_drf_chart_of_account-1.0.0.dist-info/RECORD
